mcp_software_ccopyright/__init__.py
mcp_software_ccopyright/__main__.py
mcp_software_ccopyright/cli.py
mcp_software_ccopyright/crew.py
mcp_software_ccopyright/server.py
mcp_software_ccopyright/yu/__init__.py
mcp_software_ccopyright/yu/file_info.py
mcp_software_ccopyright/yu/project.py
mcp_software_ccopyright/yu/project_info.py
mcp_software_ccopyright/yu/project_processor.py
mcp_software_ccopyright/yu/processors/__init__.py
mcp_software_ccopyright/yu/processors/blank_line_filter.py
mcp_software_ccopyright/yu/processors/c_style_comment_block_filter.py
mcp_software_ccopyright/yu/processors/comment_block_filter.py
mcp_software_ccopyright/yu/processors/css_processor.py
mcp_software_ccopyright/yu/processors/double_slash_comment_filter.py
mcp_software_ccopyright/yu/processors/go_processor.py
mcp_software_ccopyright/yu/processors/html_comment_block_filter.py
mcp_software_ccopyright/yu/processors/html_processor.py
mcp_software_ccopyright/yu/processors/java_processor.py
mcp_software_ccopyright/yu/processors/js_processor.py
mcp_software_ccopyright/yu/processors/oc_processor.py
mcp_software_ccopyright/yu/processors/php_processor.py
mcp_software_ccopyright/yu/processors/swift_processor.py
mcp_software_ccopyright-0.1.10.dist-info/licenses/LICENSE
mcp_software_ccopyright-0.1.10.dist-info/METADATA
mcp_software_ccopyright-0.1.10.dist-info/WHEEL
mcp_software_ccopyright-0.1.10.dist-info/entry_points.txt
mcp_software_ccopyright-0.1.10.dist-info/top_level.txt
mcp_software_ccopyright-0.1.10.dist-info/RECORD
