Metadata-Version: 2.4
Name: mcp-software-ccopyright
Version: 0.1.10
Summary: 软著申请大师
Requires-Python: >=3.10
License-File: LICENSE
Requires-Dist: mcp[cli]>=1.11.0
Requires-Dist: python-docx
Dynamic: license-file
